sqini/__init__.py
SQIni-0.0.6.dist-info/LICENSE
SQIni-0.0.6.dist-info/METADATA
SQIni-0.0.6.dist-info/WHEEL
SQIni-0.0.6.dist-info/entry_points.txt
SQIni-0.0.6.dist-info/top_level.txt
SQIni-0.0.6.dist-info/RECORD
