Metadata-Version: 2.1
Name: SQIni
Version: 0.0.6
Summary: connect table settings of a sqlite database with a ini file for better editing 
Home-page: https://github.com/princessmiku/SQIni
Author: Miku
License: MIT
Keywords: python,sqlite3,sqlite,ini,sqini,orm,database
Platform: UNKNOWN
Classifier: Programming Language :: Python :: 3.6
Classifier: Programming Language :: Python :: 3.7
Classifier: Programming Language :: Python :: 3.8
License-File: LICENSE
